ez_animate/__init__.py
ez_animate/animation_base.py
ez_animate/classification_animation.py
ez_animate/clustering_animation.py
ez_animate/forecasting_animation.py
ez_animate/regression_animation.py
ez_animate/transformation_animation.py
ez_animate/utils.py
ez_animate-0.1.1.dist-info/METADATA
ez_animate-0.1.1.dist-info/WHEEL
ez_animate-0.1.1.dist-info/licenses/LICENSE
ez_animate-0.1.1.dist-info/RECORD
