Metadata-Version: 2.4
Name: ez-animate
Version: 0.1.1
Summary: A simple package to streamline Matplotlib animations.
Project-URL: Homepage, https://github.com/SantiagoEnriqueGA/ez-animate
Project-URL: Repository, https://github.com/SantiagoEnriqueGA/ez-animate
Author-email: Santiago Gonzalez <sega97@gmail.com>
License: MIT License
License-File: LICENSE
Classifier: Development Status :: 3 - Alpha
Classifier: Intended Audience :: Developers
Classifier: Intended Audience :: Science/Research
Classifier: License :: OSI Approved :: MIT License
Classifier: Operating System :: OS Independent
Classifier: Programming Language :: Python :: 3
Classifier: Programming Language :: Python :: 3.9
Classifier: Programming Language :: Python :: 3.10
Classifier: Programming Language :: Python :: 3.11
Classifier: Programming Language :: Python :: 3.12
Classifier: Topic :: Scientific/Engineering :: Visualization
Requires-Python: >=3.9
Requires-Dist: matplotlib>=3
Requires-Dist: numpy>=2
Requires-Dist: scipy>=1.10
Provides-Extra: dev
Requires-Dist: build>=1.2; extra == 'dev'
Requires-Dist: mkdocs-material>=9.5; extra == 'dev'
Requires-Dist: mkdocs>=1.6; extra == 'dev'
Requires-Dist: pre-commit; extra == 'dev'
Requires-Dist: pygments; extra == 'dev'
Requires-Dist: pymdown-extensions; extra == 'dev'
Requires-Dist: pytest-cov; extra == 'dev'
Requires-Dist: pytest>=8.0; extra == 'dev'
Requires-Dist: ruff; extra == 'dev'
Requires-Dist: sega-learn; extra == 'dev'
Requires-Dist: twine>=5.0; extra == 'dev'
Provides-Extra: docs
Requires-Dist: mkdocs-material>=9.5; extra == 'docs'
Requires-Dist: mkdocs>=1.6; extra == 'docs'
Requires-Dist: pygments; extra == 'docs'
Requires-Dist: pymdown-extensions; extra == 'docs'
Provides-Extra: lint
Requires-Dist: ruff; extra == 'lint'
Provides-Extra: test
Requires-Dist: pytest-cov; extra == 'test'
Requires-Dist: pytest>=8.0; extra == 'test'
Requires-Dist: sega-learn; extra == 'test'
